MANIFEST.in
setup.cfg
setup.py
django_mce_pygments/__init__.py
django_mce_pygments/models.py
django_mce_pygments/urls.py
django_mce_pygments/views.py
django_mce_pygments.egg-info/PKG-INFO
django_mce_pygments.egg-info/SOURCES.txt
django_mce_pygments.egg-info/dependency_links.txt
django_mce_pygments.egg-info/not-zip-safe
django_mce_pygments.egg-info/requires.txt
django_mce_pygments.egg-info/top_level.txt
django_mce_pygments/static/css/pygmentsplugin.css
django_mce_pygments/static/mezzanine/tinymce/plugins/pygments/editor_plugin.js
django_mce_pygments/static/mezzanine/tinymce/plugins/pygments/editor_plugin_src.js
django_mce_pygments/static/mezzanine/tinymce/plugins/pygments/img/pygments.gif
django_mce_pygments/templates/pygments/pygments.html
django_mce_pygments/templates/pygments/source_link.html