Metadata-Version: 1.1
Name: django_mce_pygments
Version: 0.1.3
Summary: Django app that provides a pygments plugin for tinymce and backend functionality. Particularly useful for Mezzanine
Home-page: https://github.com/seanodonnell/django_mce_pygments
Author: Sean O'Donnell
Author-email: sean@odonnell.nu
License: UNKNOWN
Download-URL: https://github.com/seanodonnell/django_mce_pygments/archive/master.zip
Keywords: django,tinymce,pygments,mezzanine
Platform: UNKNOWN
Classifier: Programming Language :: Python
Classifier: Development Status :: 4 - Beta
Classifier: Environment :: Plugins
Classifier: Framework :: Django
Classifier: Intended Audience :: Developers
Classifier: License :: OSI Approved :: GNU Lesser General Public License v2 (LGPLv2)
